{
  "config": {
    "enabled": true,
    "minConsensusWallets": 3,
    "trackHip3": true
  },
  "state": {
    "summary": {
      "generatedAt": "2026-04-20T12:48:57.100584Z",
      "overallBias": "mixed",
      "consensus": [
        {
          "coin": "HYPE",
          "side": "short",
          "walletCount": 7,
          "totalValue": 36644019.77,
          "wallets": [
            {
              "address": "0x939f95036d2e7b6d7419ec072bf9d967352204d2",
              "alias": "wallet-24",
              "value": 22957426.94
            },
            {
              "address": "0x8def9f50456c6c4e37fa5d3d57f108ed23992dae",
              "alias": "wallet-26",
              "value": 4800818.21
            },
            {
              "address": "0xa87a233e8a7d8951ff790a2e39738086cb5f71b7",
              "alias": "wallet-27",
              "value": 4688173.62
            },
            {
              "address": "0xb3e475368ed0fa0ad23c04de0423d48a0758806f",
              "alias": "wallet-22",
              "value": 3317760.0
            },
            {
              "address": "0x3d89bcea338f35edfaeb313b1c713978c6dceb14",
              "alias": "wallet-9",
              "value": 413854.7
            },
            {
              "address": "0x9c2a2a966ed8e47f0c8b7e2ec2b91424f229f6a8",
              "alias": "wallet-12",
              "value": 259870.45
            },
            {
              "address": "0xad59ed47c226987cf458a63428ca10887773ba81",
              "alias": "wallet-19",
              "value": 206115.84
            }
          ]
        },
        {
          "coin": "BTC",
          "side": "long",
          "walletCount": 6,
          "totalValue": 43047402.84,
          "wallets": [
            {
              "address": "0x939f95036d2e7b6d7419ec072bf9d967352204d2",
              "alias": "wallet-24",
              "value": 31840322.23
            },
            {
              "address": "0x350e33a777d510616fbdb483d1de3b50d1edfcfb",
              "alias": "wallet-8",
              "value": 6017840.0
            },
            {
              "address": "0x932bdd2d5e21475e62d2fea8158fc5974507cb1a",
              "alias": "wallet-6",
              "value": 2937236.24
            },
            {
              "address": "0x63d417a577b50c96f4f09148d4e4d70950db0522",
              "alias": "wallet-13",
              "value": 809926.04
            },
            {
              "address": "0xc9e839a529d1a3a46e2b48d20c461d4afecb72e4",
              "alias": "wallet-2",
              "value": 745912.77
            },
            {
              "address": "0x95fde6cf0d305078b7eeac44182a931c169dd947",
              "alias": "wallet-11",
              "value": 696165.55
            }
          ]
        },
        {
          "coin": "OIL",
          "side": "short",
          "walletCount": 6,
          "totalValue": 9253020.18,
          "wallets": [
            {
              "address": "0xe9ffe7698f46f96f980f2877e18c43f5b4165903",
              "alias": "wallet-3",
              "value": 7581252.0
            },
            {
              "address": "0x1f67d79afc8d0e7609ddba6c9b657cc635f69981",
              "alias": "wallet-10",
              "value": 609498.13
            },
            {
              "address": "0x1f67d79afc8d0e7609ddba6c9b657cc635f69981",
              "alias": "wallet-10",
              "value": 522414.59
            },
            {
              "address": "0x1f67d79afc8d0e7609ddba6c9b657cc635f69981",
              "alias": "wallet-10",
              "value": 435362.41
            },
            {
              "address": "0xe9ffe7698f46f96f980f2877e18c43f5b4165903",
              "alias": "wallet-3",
              "value": 104473.2
            },
            {
              "address": "0x1f67d79afc8d0e7609ddba6c9b657cc635f69981",
              "alias": "wallet-10",
              "value": 19.86
            }
          ]
        },
        {
          "coin": "BTC",
          "side": "short",
          "walletCount": 5,
          "totalValue": 20304399.02,
          "wallets": [
            {
              "address": "0x418aa6bf98a2b2bc93779f810330d88cde488888",
              "alias": "wallet-23",
              "value": 11659565.0
            },
            {
              "address": "0x09bc1cf4d9f0b59e1425a8fde4d4b1f7d3c9410d",
              "alias": "wallet-25",
              "value": 8057364.21
            },
            {
              "address": "0xad59ed47c226987cf458a63428ca10887773ba81",
              "alias": "wallet-19",
              "value": 421248.8
            },
            {
              "address": "0x6559e0678d8b33de20dacafc36182fb643a9d297",
              "alias": "wallet-16",
              "value": 165647.82
            },
            {
              "address": "0x1f67d79afc8d0e7609ddba6c9b657cc635f69981",
              "alias": "wallet-10",
              "value": 573.2
            }
          ]
        },
        {
          "coin": "ETH",
          "side": "short",
          "walletCount": 4,
          "totalValue": 19108892.79,
          "wallets": [
            {
              "address": "0x418aa6bf98a2b2bc93779f810330d88cde488888",
              "alias": "wallet-23",
              "value": 12257310.0
            },
            {
              "address": "0x9c2a2a966ed8e47f0c8b7e2ec2b91424f229f6a8",
              "alias": "wallet-12",
              "value": 4859607.91
            },
            {
              "address": "0x8b0be882a693ad3849f9bfde6951ec36489f30be",
              "alias": "wallet-4",
              "value": 1853212.88
            },
            {
              "address": "0xad59ed47c226987cf458a63428ca10887773ba81",
              "alias": "wallet-19",
              "value": 138762.0
            }
          ]
        },
        {
          "coin": "XYZ100",
          "side": "long",
          "walletCount": 3,
          "totalValue": 24658191.71,
          "wallets": [
            {
              "address": "0x5d2f4460ac3514ada79f5d9838916e508ab39bb7",
              "alias": "wallet-21",
              "value": 17025407.69
            },
            {
              "address": "0xe9ffe7698f46f96f980f2877e18c43f5b4165903",
              "alias": "wallet-3",
              "value": 7630547.55
            },
            {
              "address": "0x1f67d79afc8d0e7609ddba6c9b657cc635f69981",
              "alias": "wallet-10",
              "value": 2236.47
            }
          ]
        },
        {
          "coin": "SP500",
          "side": "long",
          "walletCount": 3,
          "totalValue": 16072772.44,
          "wallets": [
            {
              "address": "0xe9ffe7698f46f96f980f2877e18c43f5b4165903",
              "alias": "wallet-3",
              "value": 12310475.86
            },
            {
              "address": "0x5d2f4460ac3514ada79f5d9838916e508ab39bb7",
              "alias": "wallet-21",
              "value": 3195572.81
            },
            {
              "address": "0x58cbd807135f66e8c9b4f39eea92a612b477bf00",
              "alias": "wallet-7",
              "value": 566723.76
            }
          ]
        },
        {
          "coin": "SOL",
          "side": "short",
          "walletCount": 3,
          "totalValue": 5777441.71,
          "wallets": [
            {
              "address": "0xa87a233e8a7d8951ff790a2e39738086cb5f71b7",
              "alias": "wallet-27",
              "value": 3009750.12
            },
            {
              "address": "0x8b0be882a693ad3849f9bfde6951ec36489f30be",
              "alias": "wallet-4",
              "value": 2567378.8
            },
            {
              "address": "0x9c2a2a966ed8e47f0c8b7e2ec2b91424f229f6a8",
              "alias": "wallet-12",
              "value": 200312.79
            }
          ]
        },
        {
          "coin": "SILVER",
          "side": "short",
          "walletCount": 3,
          "totalValue": 1011090.83,
          "wallets": [
            {
              "address": "0x58cbd807135f66e8c9b4f39eea92a612b477bf00",
              "alias": "wallet-7",
              "value": 937205.85
            },
            {
              "address": "0xad59ed47c226987cf458a63428ca10887773ba81",
              "alias": "wallet-19",
              "value": 71652.6
            },
            {
              "address": "0xe9ffe7698f46f96f980f2877e18c43f5b4165903",
              "alias": "wallet-3",
              "value": 2232.38
            }
          ]
        },
        {
          "coin": "HIMS",
          "side": "short",
          "walletCount": 3,
          "totalValue": 899002.64,
          "wallets": [
            {
              "address": "0xe9ffe7698f46f96f980f2877e18c43f5b4165903",
              "alias": "wallet-3",
              "value": 646728.35
            },
            {
              "address": "0x3d89bcea338f35edfaeb313b1c713978c6dceb14",
              "alias": "wallet-9",
              "value": 134891.0
            },
            {
              "address": "0x58cbd807135f66e8c9b4f39eea92a612b477bf00",
              "alias": "wallet-7",
              "value": 117383.28
            }
          ]
        },
        {
          "coin": "OIL",
          "side": "long",
          "walletCount": 3,
          "totalValue": 790491.35,
          "wallets": [
            {
              "address": "0x58cbd807135f66e8c9b4f39eea92a612b477bf00",
              "alias": "wallet-7",
              "value": 451227.09
            },
            {
              "address": "0x54a7240cea67b8c41b7c7f2b485360f37331aef4",
              "alias": "wallet-17",
              "value": 174122.0
            },
            {
              "address": "0x58cbd807135f66e8c9b4f39eea92a612b477bf00",
              "alias": "wallet-7",
              "value": 165142.27
            }
          ]
        },
        {
          "coin": "ENA",
          "side": "short",
          "walletCount": 3,
          "totalValue": 370461.66,
          "wallets": [
            {
              "address": "0xa87a233e8a7d8951ff790a2e39738086cb5f71b7",
              "alias": "wallet-27",
              "value": 177998.77
            },
            {
              "address": "0x418aa6bf98a2b2bc93779f810330d88cde488888",
              "alias": "wallet-23",
              "value": 117000.0
            },
            {
              "address": "0x63d417a577b50c96f4f09148d4e4d70950db0522",
              "alias": "wallet-13",
              "value": 75462.89
            }
          ]
        },
        {
          "coin": "EWJ",
          "side": "long",
          "walletCount": 3,
          "totalValue": 347110.26,
          "wallets": [
            {
              "address": "0x58cbd807135f66e8c9b4f39eea92a612b477bf00",
              "alias": "wallet-7",
              "value": 205991.66
            },
            {
              "address": "0x3d89bcea338f35edfaeb313b1c713978c6dceb14",
              "alias": "wallet-9",
              "value": 71216.0
            },
            {
              "address": "0xe9ffe7698f46f96f980f2877e18c43f5b4165903",
              "alias": "wallet-3",
              "value": 69902.6
            }
          ]
        },
        {
          "coin": "SILVER",
          "side": "long",
          "walletCount": 3,
          "totalValue": 337431.2,
          "wallets": [
            {
              "address": "0xb3e475368ed0fa0ad23c04de0423d48a0758806f",
              "alias": "wallet-22",
              "value": 319279.21
            },
            {
              "address": "0x3d89bcea338f35edfaeb313b1c713978c6dceb14",
              "alias": "wallet-9",
              "value": 10190.59
            },
            {
              "address": "0x1f67d79afc8d0e7609ddba6c9b657cc635f69981",
              "alias": "wallet-10",
              "value": 7961.4
            }
          ]
        }
      ],
      "hip3Consensus": [],
      "longExposure": 97526862.45,
      "shortExposure": 106329581.59,
      "walletCount": 27
    },
    "lastCheckedAt": "2026-04-20T12:48:57.100654Z",
    "lastSentAt": "2026-04-20T11:41:30.659905Z"
  }
}
